[
  {
    "id": 1000,
    "type": "TEST",
    "startTime": {
      "base": "NOW",
      "offset": "10s"
    },
    "duration": "30m",
    "noticeAhead": "5s",
    "closeDelay": "10s"
  },
  {
    "id": 100001,
    "type": "TEST",
    "startTime": {
      "base": "NOW",
      "offset": "20s"
    },
    "duration": "30m",
    "parentId": 1000,
    "noticeAhead": "1m",
    "closeDelay": "1m",
    "eventTriggers": {
      "test": {
        "cron": "0 * * * * ?"
      }
    }
  },
  {
    "id": 200001,
    "type": "TEST",
    "startTime": {
      "base": "NOW",
      "offset": "5m"
    },
    "duration": "30m",
    "noticeAhead": "1m",
    "closeDelay": "1m",
    "eventTriggers": {
      "test": {
        "cron": "0 * * * * ?"
      }
    }
  },
  {
    "id": 300001,
    "type": "TASK",
    "startTime": {
      "base": "NOW",
      "offset": "0s"
    },
    "duration": "30m",
    "noticeAhead": "1m",
    "closeDelay": "1m"
  }
]